Workbook

Sheet Assumptions
A1: Meridian Health Network — Cost Model Assumptions
A2: All figures are illustrative, order-of-magnitude Azure retail (Pay-As-You-Go, East US) list-price approximations for 3–5 year TCO comparison purposes only — not a vendor quote, EA/MCA negotiated rate, or budget-approval figure. Blue cells are editable inputs.
A4: General
A5: Workforce headcount | B5: 4300 | C5: current-state.md §1
A6: Active patients (last 24 months) | B6: 410000 | C6: current-state.md §1
A7: Sites | B7: 46 | C7: current-state.md §1
A8: Hours per year | B8: 8760 | C8: 24 x 365
A9: Reserved Capacity / Savings Plan discount (Year 2+, ADR-038) | B9: 0.25 | C9: Illustrative 1-yr Reserved Instance / Savings Plan discount range on reservable compute/DB lines only
A11: On-Prem Baseline ('Do-Nothing') Inputs
A12: Capital refresh cost — SAN + 6 hosts + networking (one-time) | B12: 660000 | C12: current-state.md §3 (91% SAN util, 6.5yr-avg host fleet); illustrative
A13: Capital refresh amortization period (years) | B13: 5 | C13: Straight-line, for TCO comparison only
A14: Backup / tape-courier / after-hours MSP NOC, annual | B14: 150000 | C14: current-state.md §3/§1; illustrative
A15: MPLS WAN to 46 sites, annual | B15: 248400 | C15: current-state.md §4; illustrative ~$450/site/month
A16: Cyber-insurance baseline annual premium | B16: 180000 | C16: problem-statement.md §4; illustrative
A17: Cyber-insurance penalty multiplier if MFA/backup/DR conditions unmet | B17: 3 | C17: problem-statement.md §4: "up to 3x current cost"
A19: Migration Program Inputs (migration-roadmap.md, ADR-035/036/037)
A20: Program duration, Wave 0 through Wave 10 (months) | B20: 13 | C20: migration-roadmap.md diagram
A21: Azure run-rate ramp — average % of steady-state during Year 1 | B21: 0.4 | C21: Illustrative wave-weighted average; most sites cut over in the back half of the program
A22: Legacy on-prem opex continuation during Year 1 (% of full-year cost) | B22: 1 | C22: ADR-036: legacy farm stays fully operational as rollback fallback until Wave 10

Sheet AzureRunRate
A1: Azure Target-State Run-Rate — Steady State (Post Wave 10, Both Regions Where Applicable)
A3: Service / Line Item | B3: Configuration | C3: Qty | D3: Unit Rate ($) | E3: Billing Basis | F3: Annual Cost | G3: Reservable? | H3: Source / Note
A4: CareLink PM Citrix VDA compute | B4: Standard_D8s_v5, Windows Datacenter (ADR-005) | C4: 20 | D4: 1 | E4: Hourly | F4: =C4*D4*Assumptions!$B$8 -> 175200 | G4: Y | H4: ADR-005 sizing (day-1 catalog 45, autoscale floor ~7); 20 = illustrative average running fleet across business/off-hours
A5: SQL Managed Instance — primary (East US) | B5: Business Critical, 8 vCore, Zone Redundant Gen5 (ADR-006) | C5: 8 | D5: 0.78 | E5: Hourly | F5: =C5*D5*Assumptions!$B$8 -> 54662.4 | G5: Y | H5: ADR-006 sizing; rate = illustrative Business Critical Zone-Redundant vCore-hr incl. storage
A6: SQL Managed Instance — DR (West US) | B6: Matching Business Critical instance, auto-failover group (ADR-006) | C6: 8 | D6: 0.78 | E6: Hourly | F6: =C6*D6*Assumptions!$B$8 -> 54662.4 | G6: Y | H6: ADR-004/006: warm standby must match primary, not a smaller stand-in
A7: App Service Premium v3 (Portal) | B7: P1v3 Linux, autoscale 3-10 (ADR-010) | C7: 5 | D7: 0.146 | E7: Hourly | F7: =C7*D7*Assumptions!$B$8 -> 6394.8 | G7: Y | H7: ADR-010 sizing; 5 = illustrative average across the 3-10 autoscale range
A8: Azure Functions Premium (LinkEngine) | B8: EP1 x4 apps, shared plan, 1 Always Ready each (ADR-008) | C8: 4 | D8: 0.173 | E8: Hourly | F8: =C8*D8*Assumptions!$B$8 -> 6061.92 | G8: Y | H8: ADR-008 sizing; excludes minor consumption-based burst execution
A9: Service Bus Premium — primary | B9: 1 Messaging Unit (ADR-011) | C9: 1 | D9: 677 | E9: Monthly | F9: =C9*D9*12 -> 8124 | G9: N | H9: ADR-011 sizing
A10: Service Bus Premium — Geo-DR secondary | B10: 1 Messaging Unit, West US namespace (ADR-011) | C10: 1 | D10: 677 | E10: Monthly | F10: =C10*D10*12 -> 8124 | G10: N | H10: ADR-011: Geo-DR secondary namespace billed at full rate (topology-only replication)
A11: API Management Premium — primary | B11: 1 scale unit (Section 1 service mapping) | C11: 1 | D11: 2795 | E11: Monthly | F11: =C11*D11*12 -> 33540 | G11: N | H11: Premium tier required for VNet integration + Strangler Fig ingress
A12: API Management Premium — DR scale unit | B12: 1 additional scale unit, West US | C12: 1 | D12: 2795 | E12: Monthly | F12: =C12*D12*12 -> 33540 | G12: N | H12: Multi-region APIM deployment for DR
A13: Azure Front Door Premium | B13: Base + WAF + data transfer (ADR-010) | C13: 1 | D13: 667 | E13: Monthly | F13: =C13*D13*12 -> 8004 | G13: N | H13: Illustrative base + usage blend
A14: Azure Site Recovery | B14: Golden-image / management-tier protected instances (ADR-004/§8) | C14: 5 | D14: 25 | E14: Monthly | F14: =C14*D14*12 -> 1500 | G14: N | H14: VDA session hosts are ephemeral/non-persistent (ADR-005) and rebuilt from image on failover, not individually ASR-protected
A15: Blob/Backup storage (GRS + immutable, both regions) | B15: ~200 TB blended hot/cool/archive tiers | C15: 200000 | D15: 0.02 | E15: Monthly-per-GB | F15: =C15*D15*12 -> 48000 | G15: N | H15: Includes ADR-037 Wave-0 immutable retention-lock backup target
A16: Microsoft Sentinel (SIEM) | B16: ~50 GB/day ingestion, combined Sentinel + Log Analytics | C16: 50 | D16: 2.46 | E16: Daily-per-GB | F16: =C16*D16*365 -> 44895 | G16: N | H16: Illustrative commit-tier blended rate
A17: Microsoft Entra ID P2 (workforce Conditional Access/MFA) | B17: Per-user/month, all workforce | C17: 4300 | D17: 9 | E17: Monthly-per-user | F17: =C17*D17*12 -> 464400 | G17: N | H17: ADR-009/ADR-037; LARGEST single line — verify against any existing M365/EMS E5 licensing before budgeting (not resolved here)
A18: Microsoft Entra External ID (patient CIAM) | B18: Monthly Active Users beyond free tier | C18: 73000 | D18: 0.01 | E18: Monthly-per-MAU | F18: =C18*D18*12 -> 8760 | G18: N | H18: ADR-009; ~30% of active patients assumed to engage portal monthly, less a 50,000-MAU free tier
A19: Retained hybrid connectivity (post-decommission) | B19: Modest ExpressRoute circuit for any remaining HQ-only, out-of-scope systems | C19: 1 | D19: 1600 | E19: Monthly | F19: =C19*D19*12 -> 19200 | G19: N | H19: Temporary migration-window circuit (ADR-035) is separate — see MigrationYr1
A20: Hub networking — Azure Firewall + Bastion + DNS (both regions) | B20: Standard tier, primary + DR hub | C20: 1 | D20: 2083 | E20: Monthly | F20: =C20*D20*12 -> 24996 | G20: N | H20: azure-implementation.md hub-and-spoke; illustrative blended both-region rate
A21: Miscellaneous / contingency | B21: Key Vault transactions, DNS zones, minor services | C21: 1 | D21: 833 | E21: Monthly | F21: =C21*D21*12 -> 9996 | G21: N | H21: Buffer line, not itemized
A23: Total — Azure Steady-State Annual Run-Rate | F23: =SUM(F4:F21) -> 1010060.5
A24: of which: Reservable (RI/Savings-Plan-eligible) compute & DB lines | F24: =SUMIF(G4:G21,"Y",F4:F21) -> 296981.52

Sheet OnPremBaseline
A1: On-Prem Baseline — 'Do Nothing' / Stay-and-Refresh Scenario (Annual, Flat Across Years)
A3: Cost Component | B3: Annual Cost | C3: Source / Note
A4: Capital refresh, amortized (SAN + hosts + networking) | B4: =Assumptions!$B$12/Assumptions!$B$13 -> 132000 | C4: requirements.md: capital refresh 'due in the current on-prem model regardless'
A5: Backup / tape-courier / after-hours MSP NOC | B5: =Assumptions!$B$14 -> 150000 | C5: current-state.md §3
A6: MPLS WAN to 46 sites | B6: =Assumptions!$B$15 -> 248400 | C6: current-state.md §4
A7: Cyber-insurance premium (penalty applies — current architecture cannot meet MFA/immutable-backup/tested-DR conditions) | B7: =Assumptions!$B$16*Assumptions!$B$17 -> 540000 | C7: problem-statement.md §4
A9: Total — On-Prem Baseline, Annual | B9: =SUM(B4:B7) -> 1070400
A11: Note: staffing (16-person team) is unchanged between scenarios and excluded here as a wash — see cost-and-risk-analysis.md §1.

Sheet MigrationYr1
A1: Migration & Transition Costs — Year 1 Only (Wave 0 through Wave 10)
A3: Cost Component | B3: Cost | C3: Source / Note
A4: One-time transition costs
A5: Landing zone build & IaC development (Wave 0) | B5: 180000 | C5: Bicep modules, network, identity foundation — azure-implementation.md §14 deferred item, built here
A6: Migration execution labor, all waves (~$42K/wave average x 10 waves) | B6: 420000 | C6: migration-roadmap.md wave count; per-wave cutover engineering, testing, smoke-test gates
A7: Temporary hybrid ExpressRoute/VPN circuit (13 months) | B7: 32500 | C7: ADR-035's named networking dependency between Wave 1 and the last compute wave
A8: Citrix Cloud incremental licensing, dual-farm overlap period | B8: 60000 | C8: Both legacy and Azure Citrix fleets run simultaneously per ADR-036
A9: Clinician / front-desk training and change management | B9: 150000 | C9: migration-roadmap.md §6, explicitly deferred workstream, budgeted here
A10: Subtotal — one-time | B10: =SUM(B5:B9) -> 842500
A12: Ramped / continuing costs during Year 1
A13: Azure run-rate, ramped (wave-weighted average of steady state) | B13: =AzureRunRate!F23*Assumptions!$B$21 -> 404024.21 | C13: Most sites cut over in the back half of the program (migration-roadmap.md wave timeline)
A14: Legacy on-prem opex continuation (backup/MSP + MPLS, full year — ADR-036) | B14: =(OnPremBaseline!B5+OnPremBaseline!B6)*Assumptions!$B$22 -> 398400 | C14: ADR-036: legacy farm stays fully operational as rollback fallback until Wave 10
A15: Capital refresh — AVOIDED (migrating replaces the need for it entirely, not just defers it) | B15: 0 | C15: Real business-case point: this is $0, not deferred spend — see cost-and-risk-analysis.md
A16: Cyber-insurance premium, Year 1 (baseline rate preserved) | B16: =Assumptions!$B$16 -> 180000 | C16: ADR-037: MFA/encryption/immutable-backup quick-wins land in Wave 0, weeks into the program — no penalty
A17: Subtotal — ramped/continuing | B17: =SUM(B13:B16) -> 982424.21
A19: Total — Azure-Track Cost, Year 1 | B19: =B10+B17 -> 1824924.2

Sheet TCOSummary
A1: 5-Year (+2 Illustrative) TCO Comparison — Do-Nothing Baseline vs. Azure Migration
A2: Years 6-7 are shown only to illustrate the breakeven trend beyond the requested 3-5 year window — see cost-and-risk-analysis.md §3 for the honest read on what this comparison does and doesn't show.
A4: Scenario | B4: Year 1 | C4: Year 2 | D4: Year 3 | E4: Year 4 | F4: Year 5 | G4: Year 6 | H4: Year 7
A5: Do-Nothing Baseline (annual) | B5: =OnPremBaseline!$B$9 -> 1070400 | C5: =OnPremBaseline!$B$9 -> 1070400 | D5: =OnPremBaseline!$B$9 -> 1070400 | E5: =OnPremBaseline!$B$9 -> 1070400 | F5: =OnPremBaseline!$B$9 -> 1070400 | G5: =OnPremBaseline!$B$9 -> 1070400 | H5: =OnPremBaseline!$B$9 -> 1070400
A6: Azure Migration (annual) | B6: =MigrationYr1!$B$19 -> 1824924.2 | C6: =AzureRunRate!$F$23-AzureRunRate!$F$24*Assumptions!$B$9 -> 935815.14 | D6: =AzureRunRate!$F$23-AzureRunRate!$F$24*Assumptions!$B$9 -> 935815.14 | E6: =AzureRunRate!$F$23-AzureRunRate!$F$24*Assumptions!$B$9 -> 935815.14 | F6: =AzureRunRate!$F$23-AzureRunRate!$F$24*Assumptions!$B$9 -> 935815.14 | G6: =AzureRunRate!$F$23-AzureRunRate!$F$24*Assumptions!$B$9 -> 935815.14 | H6: =AzureRunRate!$F$23-AzureRunRate!$F$24*Assumptions!$B$9 -> 935815.14
A8: Cumulative Do-Nothing | B8: =B5 -> 1070400 | C8: =B8+C5 -> 2140800 | D8: =C8+D5 -> 3211200 | E8: =D8+E5 -> 4281600 | F8: =E8+F5 -> 5352000 | G8: =F8+G5 -> 6422400 | H8: =G8+H5 -> 7492800
A9: Cumulative Azure Migration | B9: =B6 -> 1824924.2 | C9: =B9+C6 -> 2760739.3 | D9: =C9+D6 -> 3696554.5 | E9: =D9+E6 -> 4632369.6 | F9: =E9+F6 -> 5568184.8 | G9: =F9+G6 -> 6503999.9 | H9: =G9+H6 -> 7439815
A10: Cumulative Delta (Azure minus Do-Nothing) | B10: =B9-B8 -> 754524.21 | C10: =C9-C8 -> 619939.35 | D10: =D9-D8 -> 485354.49 | E10: =E9-E8 -> 350769.63 | F10: =F9-F8 -> 216184.77 | G10: =G9-G8 -> 81599.908 | H10: =H9-H8 -> -52984.952
